Workbook
Name NativeTimeline_Order_Date: #N/A
Name Slicer_Months__Order_Date: #N/A
Name Slicer_Product_Category: #N/A
Name Slicer_Region: #N/A

Sheet monthly_sales
A3: Row Labels | B3: Sum of Sales
A4: Jan | B4: 500569
A5: Feb | B5: 374571
A6: Mar | B6: 424943
A7: Apr | B7: 448225
A8: May | B8: 541441
A9: Jun | B9: 486909
A10: Jul | B10: 288011
A11: Aug | B11: 465484
A12: Sep | B12: 362840
A13: Oct | B13: 514648
A14: Nov | B14: 349519
A15: Dec | B15: 235523
A16: Grand Total | B16: 4992683

Sheet Sheet6
A3: Row Labels
A4: Beauty
A5: Clothing
A6: Electronics
A7: Furniture
A8: Grand Total

Sheet Sheet7
A3: Row Labels | B3: Average of profit_margin
A4: Beauty | B4: 464.00209
A5: Clothing | B5: 491.51169
A6: Electronics | B6: 461.30675
A7: Furniture | B7: 461.44768
A8: Grand Total | B8: 468.36455

Sheet Sheet8
A3: Row Labels | B3: Sum of Profit2
A4: East | B4: 269543.99
A5: North | B5: 271406.04
A6: South | B6: 286775.12
A7: West | B7: 397705.08
A8: Grand Total | B8: 1225430.2 | E8: =GETPIVOTDATA("Profit2",Sheet8!$A$3) -> 1225430.2

Sheet Dashboard
A3: Row Labels | B3: Sum of Sales
A4: East | B4: 1154477
A5: North | B5: 1072163
A6: South | B6: 1103292
A7: West | B7: 1662751
A8: Grand Total | B8: 4992683
A14: =SUM(Table1_1[Sales]) -> 4992683
E22: =KPIs!F5=GETPIVOTDATA("Sales",KPIs!$A$3) -> FALSE
C24: = | H24: =GETPIVOTDATA("Profit2",Sheet8!$A$3) -> 1225430.2

Sheet Sheet11

Sheet KPIs
E1: =SUM(Table1_1[Profit2]) -> 1225430.2 | F1: =AVERAGE(Table1_1[profit_margin]) -> 468.36455
A3: Row Labels | B3: Sum of Sales
A4: East | B4: 1154477
A5: North | B5: 1072163
A6: South | B6: 1103292
A7: West | B7: 1662751
A8: Grand Total | B8: 4992683 | I8: =GETPIVOTDATA("Sales",KPIs!$A$3) -> 4992683
F10: =KPIs!I8 -> 4992683
G13: =I6=GETPIVOTDATA("Sales",KPIs!$A$3)=GETPIVOTDATA("Sales",KPIs!$A$3) -> FALSE

Sheet Table1
A1: Order_ID | B1: Order_Date | C1: Customer_ID | D1: Region | E1: Product_Category | F1: Product_Name | G1: Quantity | H1: Unit_Price | I1: Sales | J1: Profit2 | K1: profit_margin
A2: ORD1000 | B2: 45466 | C2: CUST22 | D2: East | E2: Beauty | F2: Perfume | G2: 1 | H2: 4311 | I2: 4311 | J2: 1288.51 | K2: =Table1_1[[#This Row],[Sales]]/Table1_1[[#This Row],[Profit2]]*100 -> 334.57249
A3: ORD1001 | B3: 45395 | C3: CUST52 | D3: West | E3: Beauty | F3: Perfume | G3: 9 | H3: 692 | I3: 6228 | J3: 924.3 | K3: =Table1_1[[#This Row],[Sales]]/Table1_1[[#This Row],[Profit2]]*100 -> 673.80721
A4: ORD1002 | B4: 45588 | C4: CUST138 | D4: North | E4: Clothing | F4: T-Shirt | G4: 8 | H4: 1331 | I4: 10648 | J4: 1235.77 | K4: =Table1_1[[#This Row],[Sales]]/Table1_1[[#This Row],[Profit2]]*100 -> 861.64901
A5: ORD1003 | B5: 45421 | C5: CUST141 | D5: East | E5: Electronics | F5: Tablet | G5: 6 | H5: 3721 | I5: 22326 | J5: 5433.51 | K5: =Table1_1[[#This Row],[Sales]]/Table1_1[[#This Row],[Profit2]]*100 -> 410.89462
A6: ORD1004 | B6: 45632 | C6: CUST35 | D6: East | E6: Beauty | F6: Perfume | G6: 7 | H6: 510 | I6: 3570 | J6: 1182.09 | K6: =Table1_1[[#This Row],[Sales]]/Table1_1[[#This Row],[Profit2]]*100 -> 302.00746 | N6: Row Labels | O6: Sum of Sales
A7: ORD1005 | B7: 45406 | C7: CUST106 | D7: West | E7: Beauty | F7: Face Cream | G7: 3 | H7: 938 | I7: 2814 | J7: 285.02 | K7: =Table1_1[[#This Row],[Sales]]/Table1_1[[#This Row],[Profit2]]*100 -> 987.29914 | N7: Beauty | O7: 1318811
A8: ORD1006 | B8: 45377 | C8: CUST110 | D8: North | E8: Furniture | F8: Sofa | G8: 1 | H8: 3441 | I8: 3441 | J8: 1008.41 | K8: =Table1_1[[#This Row],[Sales]]/Table1_1[[#This Row],[Profit2]]*100 -> 341.23025 | N8: Clothing | O8: 1184465
A9: ORD1007 | B9: 45484 | C9: CUST41 | D9: North | E9: Beauty | F9: Shampoo | G9: 5 | H9: 745 | I9: 3725 | J9: 1086.93 | K9: =Table1_1[[#This Row],[Sales]]/Table1_1[[#This Row],[Profit2]]*100 -> 342.70836 | N9: Electronics | O9: 1280892
A10: ORD1008 | B10: 45298 | C10: CUST132 | D10: East | E10: Beauty | F10: Perfume | G10: 2 | H10: 2661 | I10: 5322 | J10: 1723.23 | K10: =Table1_1[[#This Row],[Sales]]/Table1_1[[#This Row],[Profit2]]*100 -> 308.83863 | N10: Furniture | O10: 1208515
A11: ORD1009 | B11: 45540 | C11: CUST29 | D11: South | E11: Furniture | F11: Bed | G11: 5 | H11: 4546 | I11: 22730 | J11: 7358.84 | K11: =Table1_1[[#This Row],[Sales]]/Table1_1[[#This Row],[Profit2]]*100 -> 308.8802 | N11: Grand Total | O11: 4992683
A12: ORD1010 | B12: 45646 | C12: CUST10 | D12: East | E12: Clothing | F12: Shoes | G12: 8 | H12: 2004 | I12: 16032 | J12: 5001.89 | K12: =Table1_1[[#This Row],[Sales]]/Table1_1[[#This Row],[Profit2]]*100 -> 320.51884
A13: ORD1011 | B13: 45522 | C13: CUST28 | D13: East | E13: Beauty | F13: Face Cream | G13: 9 | H13: 3412 | I13: 30708 | J13: 6451.58 | K13: =Table1_1[[#This Row],[Sales]]/Table1_1[[#This Row],[Profit2]]*100 -> 475.97643
A14: ORD1012 | B14: 45440 | C14: CUST21 | D14: East | E14: Furniture | F14: Chair | G14: 2 | H14: 4010 | I14: 8020 | J14: 2427.2 | K14: =Table1_1[[#This Row],[Sales]]/Table1_1[[#This Row],[Profit2]]*100 -> 330.42189
A15: ORD1013 | B15: 45636 | C15: CUST119 | D15: East | E15: Electronics | F15: Headphones | G15: 3 | H15: 1013 | I15: 3039 | J15: 1101.62 | K15: =Table1_1[[#This Row],[Sales]]/Table1_1[[#This Row],[Profit2]]*100 -> 275.86645
A16: ORD1014 | B16: 45636 | C16: CUST147 | D16: West | E16: Clothing | F16: Shoes | G16: 3 | H16: 4324 | I16: 12972 | J16: 3018.38 | K16: =Table1_1[[#This Row],[Sales]]/Table1_1[[#This Row],[Profit2]]*100 -> 429.76696
A17: ORD1015 | B17: 45571 | C17: CUST77 | D17: North | E17: Electronics | F17: Laptop | G17: 1 | H17: 2232 | I17: 2232 | J17: 262.54 | K17: =Table1_1[[#This Row],[Sales]]/Table1_1[[#This Row],[Profit2]]*100 -> 850.15617
A18: ORD1016 | B18: 45498 | C18: CUST39 | D18: West | E18: Electronics | F18: Tablet | G18: 8 | H18: 4772 | I18: 38176 | J18: 6448.55 | K18: =Table1_1[[#This Row],[Sales]]/Table1_1[[#This Row],[Profit2]]*100 -> 592.00906
A19: ORD1017 | B19: 45347 | C19: CUST103 | D19: West | E19: Furniture | F19: Bed | G19: 6 | H19: 4613 | I19: 27678 | J19: 8369.51 | K19: =Table1_1[[#This Row],[Sales]]/Table1_1[[#This Row],[Profit2]]*100 -> 330.70036
A20: ORD1018 | B20: 45629 | C20: CUST137 | D20: West | E20: Beauty | F20: Shampoo | G20: 8 | H20: 444 | I20: 3552 | J20: 1073.08 | K20: =Table1_1[[#This Row],[Sales]]/Table1_1[[#This Row],[Profit2]]*100 -> 331.0098
A21: ORD1019 | B21: 45412 | C21: CUST126 | D21: East | E21: Furniture | F21: Table | G21: 9 | H21: 4992 | I21: 44928 | J21: 7682.12 | K21: =Table1_1[[#This Row],[Sales]]/Table1_1[[#This Row],[Profit2]]*100 -> 584.83856
A22: ORD1020 | B22: 45399 | C22: CUST30 | D22: South | E22: Furniture | F22: Bookshelf | G22: 5 | H22: 471 | I22: 2355 | J22: 642.91 | K22: =Table1_1[[#This Row],[Sales]]/Table1_1[[#This Row],[Profit2]]*100 -> 366.30322
A23: ORD1021 | B23: 45317 | C23: CUST111 | D23: North | E23: Furniture | F23: Bookshelf | G23: 3 | H23: 3711 | I23: 11133 | J23: 4394.3 | K23: =Table1_1[[#This Row],[Sales]]/Table1_1[[#This Row],[Profit2]]*100 -> 253.35093
... A401: ORD1399 | B401: 45365 | C401: CUST20 | D401: North | E401: Clothing | F401: T-Shirt | G401: 2 | H401: 2347 | I401: 4694 | J401: 1761.68 | K401: =Table1_1[[#This Row],[Sales]]/Table1_1[[#This Row],[Profit2]]*100 -> 266.45021

Sheet regional_total_sales
A3: Row Labels | B3: Sum of Sales
A4: East | B4: 1154477
A5: North | B5: 1072163
A6: South | B6: 1103292
A7: West | B7: 1662751
A8: Grand Total | B8: 4992683

Sheet top_5_products
A3: Row Labels | B3: Sum of Sales
A4: Bed | B4: 305879
A5: Chair | B5: 318251
A6: Lotion | B6: 324714
A7: Smartwatch | B7: 315340
A8: Tablet | B8: 358373
A9: Grand Total | B9: 1622557

Sheet Sheet1
A1: Order_ID | B1: Order_Date | C1: Customer_ID | D1: Region | E1: Product_Category | F1: Product_Name | G1: Quantity | H1: Unit_Price | I1: Sales | J1: Profit | K1: Sales_check | L1: Profit_margin%
A2: ORD1000 | B2: 45466 | C2: CUST22 | D2: East | E2: Beauty | F2: Perfume | G2: 1 | H2: 4311 | I2: 4311 | J2: =IF(ISBLANK(I2),$J$2:$J$401,I2) -> 4311 | K2: =IF(Table1[[#This Row],[Quantity]]*Table1[[#This Row],[Unit_Price]]=Table1[[#This Row],[Sales]],"Match","Mismatch") -> Match | L2: =Table1[[#This Row],[Profit]]/Table1[[#This Row],[Sales]]*100 -> 100
A3: ORD1001 | B3: 45395 | C3: CUST52 | D3: West | E3: Beauty | F3: Perfume | G3: 9 | H3: 692 | I3: 6228 | J3: =IF(ISBLANK(I3),$J$2:$J$401,I3) -> 6228 | K3: =IF(Table1[[#This Row],[Quantity]]*Table1[[#This Row],[Unit_Price]]=Table1[[#This Row],[Sales]],"Match","Mismatch") -> Match | L3: =Table1[[#This Row],[Profit]]/Table1[[#This Row],[Sales]]*100 -> 100
A4: ORD1002 | B4: 45588 | C4: CUST138 | D4: North | E4: Clothing | F4: T-Shirt | G4: 8 | H4: 1331 | I4: 10648 | J4: =IF(ISBLANK(I4),$J$2:$J$401,I4) -> 10648 | K4: =IF(Table1[[#This Row],[Quantity]]*Table1[[#This Row],[Unit_Price]]=Table1[[#This Row],[Sales]],"Match","Mismatch") -> Match | L4: =Table1[[#This Row],[Profit]]/Table1[[#This Row],[Sales]]*100 -> 100
A5: ORD1003 | B5: 45421 | C5: CUST141 | D5: East | E5: Electronics | F5: Tablet | G5: 6 | H5: 3721 | I5: 22326 | J5: =IF(ISBLANK(I5),$J$2:$J$401,I5) -> 22326 | K5: =IF(Table1[[#This Row],[Quantity]]*Table1[[#This Row],[Unit_Price]]=Table1[[#This Row],[Sales]],"Match","Mismatch") -> Match | L5: =Table1[[#This Row],[Profit]]/Table1[[#This Row],[Sales]]*100 -> 100
A6: ORD1004 | B6: 45632 | C6: CUST35 | D6: East | E6: Beauty | F6: Perfume | G6: 7 | H6: 510 | I6: 3570 | J6: =IF(ISBLANK(I6),$J$2:$J$401,I6) -> 3570 | K6: =IF(Table1[[#This Row],[Quantity]]*Table1[[#This Row],[Unit_Price]]=Table1[[#This Row],[Sales]],"Match","Mismatch") -> Match | L6: =Table1[[#This Row],[Profit]]/Table1[[#This Row],[Sales]]*100 -> 100
A7: ORD1005 | B7: 45406 | C7: CUST106 | D7: West | E7: Beauty | F7: Face Cream | G7: 3 | H7: 938 | I7: 2814 | J7: =IF(ISBLANK(I7),$J$2:$J$401,I7) -> 2814 | K7: =IF(Table1[[#This Row],[Quantity]]*Table1[[#This Row],[Unit_Price]]=Table1[[#This Row],[Sales]],"Match","Mismatch") -> Match | L7: =Table1[[#This Row],[Profit]]/Table1[[#This Row],[Sales]]*100 -> 100
A8: ORD1006 | B8: 45377 | C8: CUST110 | D8: North | E8: Furniture | F8: Sofa | G8: 1 | H8: 3441 | I8: 3441 | J8: =IF(ISBLANK(I8),$J$2:$J$401,I8) -> 3441 | K8: =IF(Table1[[#This Row],[Quantity]]*Table1[[#This Row],[Unit_Price]]=Table1[[#This Row],[Sales]],"Match","Mismatch") -> Match | L8: =Table1[[#This Row],[Profit]]/Table1[[#This Row],[Sales]]*100 -> 100
A9: ORD1007 | B9: 45484 | C9: CUST41 | D9: North | E9: Beauty | F9: Shampoo | G9: 5 | H9: 745 | I9: 3725 | J9: =IF(ISBLANK(I9),$J$2:$J$401,I9) -> 3725 | K9: =IF(Table1[[#This Row],[Quantity]]*Table1[[#This Row],[Unit_Price]]=Table1[[#This Row],[Sales]],"Match","Mismatch") -> Match | L9: =Table1[[#This Row],[Profit]]/Table1[[#This Row],[Sales]]*100 -> 100
A10: ORD1008 | B10: 45298 | C10: CUST132 | D10: East | E10: Beauty | F10: Perfume | G10: 2 | H10: 2661 | I10: 5322 | J10: =IF(ISBLANK(I10),$J$2:$J$401,I10) -> 5322 | K10: =IF(Table1[[#This Row],[Quantity]]*Table1[[#This Row],[Unit_Price]]=Table1[[#This Row],[Sales]],"Match","Mismatch") -> Match | L10: =Table1[[#This Row],[Profit]]/Table1[[#This Row],[Sales]]*100 -> 100
A11: ORD1009 | B11: 45540 | C11: CUST29 | D11: South | E11: Furniture | F11: Bed | G11: 5 | H11: 4546 | I11: 22730 | J11: =IF(ISBLANK(I11),$J$2:$J$401,I11) -> 22730 | K11: =IF(Table1[[#This Row],[Quantity]]*Table1[[#This Row],[Unit_Price]]=Table1[[#This Row],[Sales]],"Match","Mismatch") -> Match | L11: =Table1[[#This Row],[Profit]]/Table1[[#This Row],[Sales]]*100 -> 100
A12: ORD1010 | B12: 45646 | C12: CUST10 | D12: East | E12: Clothing | F12: Shoes | G12: 8 | H12: 2004 | I12: 16032 | J12: =IF(ISBLANK(I12),$J$2:$J$401,I12) -> 16032 | K12: =IF(Table1[[#This Row],[Quantity]]*Table1[[#This Row],[Unit_Price]]=Table1[[#This Row],[Sales]],"Match","Mismatch") -> Match | L12: =Table1[[#This Row],[Profit]]/Table1[[#This Row],[Sales]]*100 -> 100
A13: ORD1011 | B13: 45522 | C13: CUST28 | D13: East | E13: Beauty | F13: Face Cream | G13: 9 | H13: 3412 | I13: 30708 | J13: =IF(ISBLANK(I13),$J$2:$J$401,I13) -> 30708 | K13: =IF(Table1[[#This Row],[Quantity]]*Table1[[#This Row],[Unit_Price]]=Table1[[#This Row],[Sales]],"Match","Mismatch") -> Match | L13: =Table1[[#This Row],[Profit]]/Table1[[#This Row],[Sales]]*100 -> 100
... A401: ORD1399 | B401: 45365 | C401: CUST20 | D401: North | E401: Clothing | F401: T-Shirt | G401: 2 | H401: 2347 | I401: 4694 | J401: =IF(ISBLANK(I401),$J$2:$J$401,I401) -> 4694 | K401: =IF(Table1[[#This Row],[Quantity]]*Table1[[#This Row],[Unit_Price]]=Table1[[#This Row],[Sales]],"Match","Mismatch") -> Match | L401: =Table1[[#This Row],[Profit]]/Table1[[#This Row],[Sales]]*100 -> 100
